graphqlstore-3.4.0.dist-info/licenses/LICENSE
source/__init__.py
source/main.py
source/cli/__init__.py
source/cli/base.py
source/cli/core.py
source/cli/main.py
source/cli/conexion/__init__.py
source/cli/conexion/comando_conexion.py
source/cli/conexion/main.py
source/cli/database/__init__.py
source/cli/database/adaptador_database.py
source/cli/database/adaptadores/__init__.py
source/cli/database/adaptadores/mysql.py
source/cli/graphql/__init__.py
source/cli/graphql/configuracion_y_constantes.py
source/cli/graphql/exceptions.py
source/cli/graphql/mysql_generador.py
source/cli/graphql/mysql_migracion.py
source/cli/graphql/parser.py
source/cli/graphql/procesar_relaciones.py
source/cli/graphql/templates.py
source/cli/inicializar/__init__.py
source/cli/inicializar/comando_inicializar.py
source/cli/inicializar/main.py
source/cli/loaders/__init__.py
source/cli/loaders/conf_json_loader.py
source/cli/loaders/conf_loader.py
source/cli/migracion/__init__.py
source/cli/migracion/comando_migracion.py
source/cli/migracion/main.py
source/cli/probar_conexion/__init__.py
source/cli/probar_conexion/comando_probar_conexion.py
source/cli/probar_conexion/main.py
source/cli/servidor/__init__.py
source/cli/servidor/comando_servidor.py
source/cli/servidor/main.py
source/cli/utilidades/__init__.py
source/cli/utilidades/gestor_archivo.py
graphqlstore-3.4.0.dist-info/METADATA
graphqlstore-3.4.0.dist-info/WHEEL
graphqlstore-3.4.0.dist-info/entry_points.txt
graphqlstore-3.4.0.dist-info/top_level.txt
graphqlstore-3.4.0.dist-info/RECORD
