Metadata-Version: 2.4
Name: graphqlstore
Version: 3.4.0
Summary: A CLI tool for managing GraphQL stores
Author-email: adg1023 <adg1023@alu.ubu.es>
Keywords: graphql,cli,graphqlstore,graphqlstore-cli,python,javascript,typescript
Classifier: Programming Language :: Python :: 3.10
Requires-Python: >=3.10
License-File: LICENSE
Requires-Dist: rich>=14.0.0
Requires-Dist: mysql-connector-python>=9.3.0
Requires-Dist: graphql-core>=3.2.6
Provides-Extra: dev
Requires-Dist: black; extra == "dev"
Requires-Dist: flake8; extra == "dev"
Requires-Dist: mypy; extra == "dev"
Requires-Dist: pytest; extra == "dev"
Requires-Dist: pytest-cov; extra == "dev"
Requires-Dist: pylint; extra == "dev"
Requires-Dist: pre-commit; extra == "dev"
Requires-Dist: build; extra == "dev"
Dynamic: license-file
